certbot_dns_abion/__init__.py
certbot_dns_abion/py.typed
certbot_dns_abion/_internal/__init__.py
certbot_dns_abion/_internal/abion_client.py
certbot_dns_abion/_internal/dns_abion.py
certbot_dns_abion-0.2.0.dist-info/licenses/LICENSE
certbot_dns_abion-0.2.0.dist-info/METADATA
certbot_dns_abion-0.2.0.dist-info/WHEEL
certbot_dns_abion-0.2.0.dist-info/entry_points.txt
certbot_dns_abion-0.2.0.dist-info/top_level.txt
certbot_dns_abion-0.2.0.dist-info/RECORD
