Metadata-Version: 2.4
Name: certbot-dns-abion
Version: 0.2.0
Summary: Certbot DNS authenticator for Abion DNS API (community maintained, not affiliated with Abion)
License-Expression: Apache-2.0
Requires-Python: >=3.8
License-File: LICENSE
Requires-Dist: certbot>=2.6.0
Requires-Dist: requests>=2.28.0
Dynamic: license-file
